[1,["141300663","68+zItlu5GH5tbGWN1u1Cr","d56hmd/5VBh4ZdzGcieSv/","87OCaYsbhEjbLRwfkRPcnz","d0+isl2/lLL5U1RaLcwpMJ","b5TJeGkStEHZ06F2je963p","33RkXsg6hOc4qSirwFMHpn","07JS5EWlBMHJu4QF9Worwf","aa7tLJcVZIsKrBTrJousIh","a6MXkYHqxCLqE0QBc7dSOq","e4ZsQ375BFO4RCk/E3oRkf","47VAnZ5BxIF6Jq2+aguy4Y","e77gQ+2/RMAIaaz5f1t4YM","97+VESJyRIBKsOuBM5JFp3"],["value","_textureSetter"],["cc.SpriteFrame",["cc.AnimationClip",["_name","_duration","sample","wrapMode","curveData"],-1,11]],[[1,0,1,2,3,4,5]],[[[{"name":"fs_vfx_b_screen_06","rect":[1,1,147,390],"offset":[0,0],"originalSize":[147,390],"rotated":1,"capInsets":[0,0,0,0]}],[0],0,[0],[1],[0]],[[{"name":"fs_vfx_b_screen_05","rect":[393,1,147,390],"offset":[0,0],"originalSize":[147,390],"rotated":1,"capInsets":[0,0,0,0]}],[0],0,[0],[1],[0]],[[{"name":"fs_vfx_b_screen_10","rect":[1,150,147,390],"offset":[0,0],"originalSize":[147,390],"rotated":1,"capInsets":[0,0,0,0]}],[0],0,[0],[1],[0]],[[[0,"NearWin1",0.9333333333333333,15,2,[{},"comps",11,[{},"cc.Sprite",11,[{},"spriteFrame",12,[[[{"frame":0},"value",6,0],[{"frame":0.06666666666666667},"value",6,1],[{"frame":0.13333333333333333},"value",6,2],[{"frame":0.2},"value",6,3],[{"frame":0.26666666666666666},"value",6,4],[{"frame":0.3333333333333333},"value",6,5],[{"frame":0.4},"value",6,6],[{"frame":0.4666666666666667},"value",6,7],[{"frame":0.5333333333333333},"value",6,8],[{"frame":0.6},"value",6,9],[{"frame":0.6666666666666666},"value",6,10],[{"frame":0.7333333333333333},"value",6,11],[{"frame":0.8},"value",6,12],[{"frame":0.8666666666666667},"value",6,13]],11,11,11,11,11,11,11,11,11,11,11,11,11,11]]]]]],0,0,[0,0,0,0,0,0,0,0,0,0,0,0,0,0],[0,0,0,0,0,0,0,0,0,0,0,0,0,0],[1,1,2,3,4,5,6,7,8,9,10,11,12,13]],[[{"name":"fs_vfx_b_screen_00","rect":[393,150,147,390],"offset":[0,0],"originalSize":[147,390],"rotated":1,"capInsets":[0,31,0,35]}],[0],0,[0],[1],[0]],[[{"name":"fs_vfx_b_screen_02","rect":[1,299,147,390],"offset":[0,0],"originalSize":[147,390],"capInsets":[0,0,0,0]}],[0],0,[0],[1],[0]],[[{"name":"fs_vfx_b_screen_12","rect":[1,691,147,390],"offset":[0,0],"originalSize":[147,390],"rotated":1,"capInsets":[0,0,0,0]}],[0],0,[0],[1],[0]],[[{"name":"fs_vfx_b_screen_08","rect":[150,299,147,390],"offset":[0,0],"originalSize":[147,390],"capInsets":[0,0,0,0]}],[0],0,[0],[1],[0]],[[{"name":"fs_vfx_b_screen_07","rect":[299,299,147,390],"offset":[0,0],"originalSize":[147,390],"capInsets":[0,0,0,0]}],[0],0,[0],[1],[0]],[[{"name":"fs_vfx_b_screen_04","rect":[393,691,147,390],"offset":[0,0],"originalSize":[147,390],"rotated":1,"capInsets":[0,0,0,0]}],[0],0,[0],[1],[0]],[[{"name":"fs_vfx_b_screen_03","rect":[448,299,147,390],"offset":[0,0],"originalSize":[147,390],"capInsets":[0,0,0,0]}],[0],0,[0],[1],[0]],[[{"name":"fs_vfx_b_screen_01","rect":[597,299,147,390],"offset":[0,0],"originalSize":[147,390],"capInsets":[0,0,0,0]}],[0],0,[0],[1],[0]],[[{"name":"fs_vfx_b_screen_09","rect":[1,840,147,390],"offset":[0,0],"originalSize":[147,390],"rotated":1,"capInsets":[0,0,0,0]}],[0],0,[0],[1],[0]],[[{"name":"fs_vfx_b_screen_11","rect":[393,840,147,390],"offset":[0,0],"originalSize":[147,390],"rotated":1,"capInsets":[0,0,0,0]}],[0],0,[0],[1],[0]]]]